INSTALL.txt
MANIFEST.in
README.txt
setup.cfg
setup.py
lalistadesinde/__init__.py
lalistadesinde.portlet.egg-info/PKG-INFO
lalistadesinde.portlet.egg-info/SOURCES.txt
lalistadesinde.portlet.egg-info/dependency_links.txt
lalistadesinde.portlet.egg-info/entry_points.txt
lalistadesinde.portlet.egg-info/namespace_packages.txt
lalistadesinde.portlet.egg-info/not-zip-safe
lalistadesinde.portlet.egg-info/paster_plugins.txt
lalistadesinde.portlet.egg-info/requires.txt
lalistadesinde.portlet.egg-info/top_level.txt
lalistadesinde/portlet/__init__.py
lalistadesinde/portlet/configure.zcml
lalistadesinde/portlet/lalistadesinde.pt