Metadata-Version: 1.0
Name: lalistadesinde.portlet
Version: 1.0
Summary: La lista de Sinde portlet for Plone
Home-page: http://lalistadesinde.net
Author: hacktivistas
Author-email: contacto@lalistadesinde.net
License: GPL
Keywords: lalistadesinde
Platform: UNKNOWN
Classifier: Framework :: Plone
Classifier: Programming Language :: Python
